airunner_nexus/__init__.py
airunner_nexus/client.py
airunner_nexus/enums.py
airunner_nexus/exceptions.py
airunner_nexus/logger.py
airunner_nexus/messagecodes.py
airunner_nexus/server.py
airunner_nexus/settings.py
airunner_nexus/llm/__init__.py
airunner_nexus/llm/agent.py
airunner_nexus/llm/external_condition_stopping_criteria.py
airunner_nexus/llm/llm_handler.py
airunner_nexus/llm/rag_mixin.py
airunner_nexus/tts/__init__.py
airunner_nexus/utils/__init__.py
airunner_nexus-1.5.3.dist-info/LICENSE
airunner_nexus-1.5.3.dist-info/METADATA
airunner_nexus-1.5.3.dist-info/WHEEL
airunner_nexus-1.5.3.dist-info/top_level.txt
airunner_nexus-1.5.3.dist-info/RECORD
