Metadata-Version: 2.1
Name: airunner_nexus
Version: 1.5.3
Summary: Run a socket server for AI models.
Home-page: https://github.com/Capsize-Games/airunner_nexus
Author: Capsize LLC
Author-email: contact@capsizegames.com
License: GPL-3.0
Keywords: ai,LLM,mistral
Requires-Python: >=3.10.0
License-File: LICENSE
Requires-Dist: numpy ==1.26.4
Requires-Dist: accelerate ==0.29.2
Requires-Dist: huggingface-hub ==0.23.0
Requires-Dist: torch ==2.2.2
Requires-Dist: optimum ==1.19.1
Requires-Dist: inflect ==7.2.0
Requires-Dist: omegaconf ==2.3.0
Requires-Dist: diffusers ==0.27.2
Requires-Dist: controlnet-aux ==0.0.8
Requires-Dist: einops ==0.7.0
Requires-Dist: Pillow ==10.3.0
Requires-Dist: pyre-extensions ==0.0.30
Requires-Dist: safetensors ==0.4.3
Requires-Dist: compel ==2.0.2
Requires-Dist: tomesd ==0.1.3
Requires-Dist: transformers ==4.40.1
Requires-Dist: auto-gptq ==0.7.1
Requires-Dist: bitsandbytes ==0.43.1
Requires-Dist: datasets ==2.18.0
Requires-Dist: sentence-transformers ==2.6.1
Requires-Dist: pycountry ==23.12.11
Requires-Dist: sounddevice ==0.4.6
Requires-Dist: pyttsx3 ==2.90
Requires-Dist: peft ==0.12.0
Requires-Dist: ninja ==1.11.1.1
Requires-Dist: JIT ==0.2.7
Requires-Dist: setuptools ==69.5.1
Requires-Dist: llama-index ==0.10.32
Requires-Dist: llama-index-readers-file ==0.1.19
Requires-Dist: llama-index-readers-web ==0.1.13
Requires-Dist: llama-index-embeddings-huggingface ==0.2.3
Requires-Dist: llama-index-llms-huggingface ==0.2.6
